pycifter/__init__.py
pycifter/atom.py
pycifter/cifFileParser.py
pycifter/graph.py
pycifter/interactiveGraphs.py
pycifter/render.py
pycifter-0.1.1.dist-info/licenses/LICENSE
pycifter-0.1.1.dist-info/METADATA
pycifter-0.1.1.dist-info/WHEEL
pycifter-0.1.1.dist-info/top_level.txt
pycifter-0.1.1.dist-info/RECORD
