Metadata-Version: 2.4
Name: pycifter
Version: 0.1.1
Summary: A tool for analyzing CIF files and conduct large scale analysis on them.
Author-email: Tej Gumaste <tej.gumaste@gmail.com>
License: MIT
Project-URL: Homepage, https://github.com/Vegito2367/PyCIFTer
Project-URL: Issues, https://github.com/Vegito2367/PyCIFTer/issues
Requires-Python: >=3.10
License-File: LICENSE
Requires-Dist: numpy
Requires-Dist: matplotlib
Requires-Dist: xlsxwriter
Requires-Dist: plotly
Requires-Dist: pandas
Dynamic: license-file
